{
  "title": "Your New Year's surprise. Forever.",
  "subtitle": "Your New Year's surprise. Forever.",
  "title_text_color": "#FFFFFF",
  "subtitle_text_color": "#FFFFFF",
  "countdown": true,
  "right_padding": "0",
  "deadline": "2026-01-13",
  "background": {
    "start_color": "#F6A8B6",
    "end_color": "#FFD7A8",
    "direction": "left-to-right"
  },
  "title_font_size": "16",
  "subtitle_font_size": "14",
  "animation": {
    "type": "https://raw.githubusercontent.com/filipembcruz/lifeapp-files/main/seasonal_banner_animation.json",
    "width": "80",
    "height": "80",
    "right_padding": "8"
  },
  "translations": {
    "ar": {
      "title": "مفاجأة رأس السنة. للأبد.",
      "subtitle": "مفاجأة رأس السنة. للأبد."
    },
    "de": {
      "title": "Deine Neujahrsüberraschung.",
      "subtitle": "Deine Neujahrsüberraschung."
    },
    "fr": {
      "title": "Surprise du Nouvel An. À jamais.",
      "subtitle": "Surprise du Nouvel An. À jamais."
    },
    "it": {
      "title": "Sorpresa di Capodanno. Per sempre",
      "subtitle": "Sorpresa di Capodanno. Per sempre"
    },
    "nb": {
      "title": "Nyttårsoverraskelse. For alltid.",
      "subtitle": "Nyttårsoverraskelse. For alltid."
    },
    "pt_BR": {
      "title": "Sua surpresa de Ano Novo. Sempre.",
      "subtitle": "Sua surpresa de Ano Novo. Sempre."
    },
    "pt_PT": {
      "title": "A tua surpresa de Ano Novo. Sempre",
      "subtitle": "A tua surpresa de Ano Novo. Sempre"
    },
    "ru": {
      "title": "Твой подарок на Новый год. Вечно.",
      "subtitle": "Твой подарок на Новый год. Вечно."
    },
    "sv": {
      "title": "Din nyårsöverraskning. För evigt.",
      "subtitle": "Din nyårsöverraskning. För evigt."
    },
    "zh_Hans": {
      "title": "您的新年惊喜。永久有效。",
      "subtitle": "您的新年惊喜。永久有效。"
    },
    "zh_Hant": {
      "title": "您的新年驚喜。永久有效。",
      "subtitle": "您的新年驚喜。永久有效。"
    },
    "ja": {
      "title": "新年の驚きを、永遠に。",
      "subtitle": "新年の驚きを、永遠に。"
    },
    "ko": {
      "title": "당신의 새해 선물. 영원히.",
      "subtitle": "당신의 새해 선물. 영원히."
    },
    "da": {
      "title": "Din nytårsoverraskelse. For altid.",
      "subtitle": "Din nytårsoverraskelse. For altid."
    },
    "es": {
      "title": "Tu sorpresa de Año Nuevo. Siempre.",
      "subtitle": "Tu sorpresa de Año Nuevo. Siempre."
    },
    "nl": {
      "title": "Jouw nieuwjaarsverrassing. Altijd.",
      "subtitle": "Jouw nieuwjaarsverrassing. Altijd."
    },
    "fi": {
      "title": "Uudenvuoden yllätys. Ikuisesti.",
      "subtitle": "Uudenvuoden yllätys. Ikuisesti."
    },
    "ro": {
      "title": "Surpriza ta de Anul Nou. Mereu.",
      "subtitle": "Surpriza ta de Anul Nou. Mereu."
    },
    "uk": {
      "title": "Твій сюрприз на Новий рік. Назавжди",
      "subtitle": "Твій сюрприз на Новий рік. Назавжди"
    }
  }
}